setup.py
distributions/Binomialdistribution.py
distributions/Gaussiandistribution.py
distributions/Generaldistribution.py
distributions/__init__.py
pybigauss.egg-info/PKG-INFO
pybigauss.egg-info/SOURCES.txt
pybigauss.egg-info/dependency_links.txt
pybigauss.egg-info/not-zip-safe
pybigauss.egg-info/top_level.txt