Metadata-Version: 1.0
Name: pybigauss
Version: 1.0.0
Summary: Gaussian and Binomial distributions
Home-page: UNKNOWN
Author: Umar Faruk Abdullahi
Author-email: ufakz99@gmail.com
License: UNKNOWN
Platform: UNKNOWN
